fetchanything/__init__.py
fetchanything/cli.py
fetchanything-0.2.0.dist-info/licenses/LICENSE
fetchanything-0.2.0.dist-info/METADATA
fetchanything-0.2.0.dist-info/WHEEL
fetchanything-0.2.0.dist-info/entry_points.txt
fetchanything-0.2.0.dist-info/top_level.txt
fetchanything-0.2.0.dist-info/RECORD
