Metadata-Version: 2.4
Name: fetchanything
Version: 0.2.0
Summary: A command-line tool to fetch files from websites recursively
Home-page: https://github.com/yourusername/fetchanything
Author: Chao-Chung Kuo
Author-email: chao-chung.kuo@rwth-aachen.de
Classifier: Programming Language :: Python :: 3
Classifier: License :: OSI Approved :: MIT License
Classifier: Operating System :: OS Independent
Requires-Python: >=3.7
License-File: LICENSE
Requires-Dist: requests>=2.31.0
Requires-Dist: beautifulsoup4>=4.12.0
Requires-Dist: tqdm>=4.66.0
Requires-Dist: argparse>=1.4.0
Requires-Dist: urllib3>=2.0.0
Dynamic: author
Dynamic: author-email
Dynamic: classifier
Dynamic: description
Dynamic: description-content-type
Dynamic: home-page
Dynamic: license-file
Dynamic: requires-dist
Dynamic: requires-python
Dynamic: summary
